pyref-0.8.2.dist-info/METADATA
pyref-0.8.2.dist-info/WHEEL
pyref-0.8.2.dist-info/licenses/LICENSE
pyref/exceptions.py
pyref/masking.py
pyref/image/extensions.py
pyref/image/__init__.py
pyref/fitting/uniaxial.py
pyref/fitting/model.py
pyref/fitting/fitters.py
pyref/fitting/structure.py
pyref/fitting/io.py
pyref/fitting/__init__.py
pyref/io/readers.py
pyref/io/__init__.py
pyref/types.py
pyref/loader.py
pyref/image.py
pyref/utils/__init__.py
pyref/__init__.py
pyref/pyref.abi3.so
pyref-0.8.2.dist-info/RECORD
