Metadata-Version: 2.3
Name: pyref
Version: 0.8.2
Classifier: License :: OSI Approved :: MIT License
Classifier: Programming Language :: Python :: 3.12
Classifier: Programming Language :: Rust
Classifier: Intended Audience :: Science/Research
Classifier: Topic :: Scientific/Engineering :: Physics
Classifier: Development Status :: 4 - Beta
Classifier: Operating System :: POSIX :: Linux
Classifier: Operating System :: Microsoft :: Windows
Classifier: Operating System :: MacOS
Requires-Dist: fastparquet >=2024.11.0
Requires-Dist: matplotlib >=3.10.3
Requires-Dist: numba >=0.61.2
Requires-Dist: numpy >=2.0
Requires-Dist: pandas >=2.2.3
Requires-Dist: periodictable >=2.0.2
Requires-Dist: polars[pandas] >=1.29.0
Requires-Dist: refnx >=0.1.57
Requires-Dist: scikit-image >=0.25.2
Requires-Dist: scikit-learn >=1.6.1
Requires-Dist: scipy >=1.15.3
Requires-Dist: seaborn >=0.13.2
Requires-Dist: sigfig >=1.3.19
Requires-Dist: sympy >=1.14.0
License-File: LICENSE
Summary: Blazingly fast X-ray reflectivity data analysis package
Keywords: X-ray,reflectivity,data,analysis
Author: Harlan Heilman Harlan.Heilman@wsu.edu
Author-email: Harlan <Harlan.Heilman@wsu.edu>
Maintainer-email: Harlan <Harlan.Heilman@wsu.edu>
License: GPL-3.0
Requires-Python: >=3.12
Project-URL: Documentation, https://wsu-carbon-lab.github.io/pyref/
Project-URL: Source, https://github.com/WSU-Carbon-Lab/pyref
